[{"th":"\/img\/furgoneta-camper\/kit-cama-ducha-VW-T6\/th_IMG_8978.JPG","origin":"\/img\/furgoneta-camper\/kit-cama-ducha-VW-T6\/T_IMG_8978.JPG","img":"\/img\/furgoneta-camper\/kit-cama-ducha-VW-T6\/T_IMG_8978.JPG"},{"th":"\/img\/furgoneta-camper\/kit-cama-ducha-VW-T6\/th_IMG_8976.JPG","origin":"\/img\/furgoneta-camper\/kit-cama-ducha-VW-T6\/T_IMG_8976.JPG","img":"\/img\/furgoneta-camper\/kit-cama-ducha-VW-T6\/T_IMG_8976.JPG"},{"th":"\/img\/furgoneta-camper\/kit-cama-ducha-VW-T6\/th_IMG_8977.JPG","origin":"\/img\/furgoneta-camper\/kit-cama-ducha-VW-T6\/T_IMG_8977.JPG","img":"\/img\/furgoneta-camper\/kit-cama-ducha-VW-T6\/T_IMG_8977.JPG"},{"th":"\/img\/furgoneta-camper\/kit-cama-ducha-VW-T6\/th_IMG_8921.JPG","origin":"\/img\/furgoneta-camper\/kit-cama-ducha-VW-T6\/T_IMG_8921.JPG","img":"\/img\/furgoneta-camper\/kit-cama-ducha-VW-T6\/T_IMG_8921.JPG"},{"th":"\/img\/furgoneta-camper\/kit-cama-ducha-VW-T6\/th_IMG_8980.JPG","origin":"\/img\/furgoneta-camper\/kit-cama-ducha-VW-T6\/T_IMG_8980.JPG","img":"\/img\/furgoneta-camper\/kit-cama-ducha-VW-T6\/T_IMG_8980.JPG"},{"th":"\/img\/furgoneta-camper\/kit-cama-ducha-VW-T6\/th_IMG_8973.JPG","origin":"\/img\/furgoneta-camper\/kit-cama-ducha-VW-T6\/T_IMG_8973.JPG","img":"\/img\/furgoneta-camper\/kit-cama-ducha-VW-T6\/T_IMG_8973.JPG"},{"th":"\/img\/furgoneta-camper\/kit-cama-ducha-VW-T6\/th_IMG_8974.JPG","origin":"\/img\/furgoneta-camper\/kit-cama-ducha-VW-T6\/T_IMG_8974.JPG","img":"\/img\/furgoneta-camper\/kit-cama-ducha-VW-T6\/T_IMG_8974.JPG"},{"th":"\/img\/furgoneta-camper\/kit-cama-ducha-VW-T6\/th_IMG_8979.JPG","origin":"\/img\/furgoneta-camper\/kit-cama-ducha-VW-T6\/T_IMG_8979.JPG","img":"\/img\/furgoneta-camper\/kit-cama-ducha-VW-T6\/T_IMG_8979.JPG"},{"th":"\/img\/furgoneta-camper\/kit-cama-ducha-VW-T6\/th_IMG_8920.JPG","origin":"\/img\/furgoneta-camper\/kit-cama-ducha-VW-T6\/T_IMG_8920.JPG","img":"\/img\/furgoneta-camper\/kit-cama-ducha-VW-T6\/T_IMG_8920.JPG"},{"th":"\/img\/furgoneta-camper\/kit-cama-ducha-VW-T6\/th_IMG_8919.JPG","origin":"\/img\/furgoneta-camper\/kit-cama-ducha-VW-T6\/T_IMG_8919.JPG","img":"\/img\/furgoneta-camper\/kit-cama-ducha-VW-T6\/T_IMG_8919.JPG"},{"th":"\/img\/furgoneta-camper\/kit-cama-ducha-VW-T6\/th_IMG_8975.JPG","origin":"\/img\/furgoneta-camper\/kit-cama-ducha-VW-T6\/T_IMG_8975.JPG","img":"\/img\/furgoneta-camper\/kit-cama-ducha-VW-T6\/T_IMG_8975.JPG"}]